myprojectdydy/__init__.py
myprojectdydy/ista/ISTA.py
myprojectdydy/ista/ISTA_l2.py
myprojectdydy/ista/L2minGD.py
myprojectdydy/ista/__init__.py
myprojectdydy/lasso/Comparision_GroupLASSO.py
myprojectdydy/lasso/GroupLasso.py
myprojectdydy/lasso/GroupLasso2.py
myprojectdydy/lasso/GroupLasso_ISTA.py
myprojectdydy/lasso/__init__.py
myprojectdydy-0.0.2.dist-info/DESCRIPTION.rst
myprojectdydy-0.0.2.dist-info/METADATA
myprojectdydy-0.0.2.dist-info/RECORD
myprojectdydy-0.0.2.dist-info/WHEEL
myprojectdydy-0.0.2.dist-info/metadata.json
myprojectdydy-0.0.2.dist-info/top_level.txt
