Metadata-Version: 2.0
Name: myprojectdydy
Version: 0.0.2
Summary: optimizers
Home-page: https://github.com/DoyeobYeo/MyProject
Author: DoyeobYeo
Author-email: greatday87@gmail.com
License: MIT
Keywords: LASSO,Group,GroupLASSO
Platform: any
Classifier: Development Status :: 3 - Alpha
Classifier: Intended Audience :: Science/Research
Classifier: License :: OSI Approved :: MIT License
Classifier: Natural Language :: English
Classifier: Operating System :: OS Independent
Classifier: Programming Language :: Python :: 3.4
Classifier: Topic :: Scientific/Engineering :: Mathematics
Requires-Dist: matplotlib (>=1.5.3)
Requires-Dist: numpy (>=1.11.2)
